nukeddit/__init__.py
nukeddit/app.py
nukeddit/nukeddit.yml.example
nukeddit/praw.ini.example
nukeddit/shredder.py
nukeddit/util.py
Nukeddit-0.2.2.dist-info/LICENSE
Nukeddit-0.2.2.dist-info/METADATA
Nukeddit-0.2.2.dist-info/WHEEL
Nukeddit-0.2.2.dist-info/entry_points.txt
Nukeddit-0.2.2.dist-info/top_level.txt
Nukeddit-0.2.2.dist-info/RECORD
