Metadata-Version: 2.1
Name: Nukeddit
Version: 0.2.2
Summary: Remove your comment history on Reddit.
Home-page: https://gitlab.com/0x00cl/nukeddit
Author: Tomas Gutierrez L.
Author-email: 0x00cl@example.com
License: FreeBSD License
Platform: UNKNOWN
Classifier: Development Status :: 3 - Alpha
Classifier: Intended Audience :: End Users/Desktop
Classifier: License :: OSI Approved :: BSD License
Classifier: Programming Language :: Python :: 3
Requires-Dist: arrow
Requires-Dist: praw (>=7)
Requires-Dist: requests
Requires-Dist: prawcore
Requires-Dist: pyyaml
Requires-Dist: argparse
Requires-Dist: appdirs
